aioload/__init__.py
aioload/plot.py
aioload/runner.py
aioload_utils/__init__.py
aioload-0.4.0.dist-info/METADATA
aioload-0.4.0.dist-info/WHEEL
aioload-0.4.0.dist-info/entry_points.txt
aioload-0.4.0.dist-info/top_level.txt
aioload-0.4.0.dist-info/RECORD
