Metadata-Version: 2.1
Name: aioload
Version: 0.4.0
Summary: Load test tool
Home-page: https://github.com/sonic182/aioload
Author: Johanderson Mogollon
Author-email: johanderson@mogollon.com.ve
License: MIT
Keywords: testing loadtest load
Platform: UNKNOWN
Classifier: Development Status :: 5 - Production/Stable
Classifier: Intended Audience :: Developers
Classifier: Topic :: Software Development
Classifier: License :: OSI Approved :: MIT License
Classifier: Programming Language :: Python :: 3.6
Classifier: Programming Language :: Python :: 3.7
Requires-Dist: aiosonic (==0.8.1)
Requires-Dist: chardet (==3.0.4)
Requires-Dist: cycler (==0.10.0)
Requires-Dist: h2 (==4.0.0)
Requires-Dist: hpack (==4.0.0)
Requires-Dist: hyperframe (==6.0.0)
Requires-Dist: kiwisolver (==1.3.1)
Requires-Dist: matplotlib (<=3.1.1)
Requires-Dist: numpy (==1.19.4)
Requires-Dist: pandas (==1.1.4)
Requires-Dist: pillow (==8.0.1)
Requires-Dist: pyparsing (==2.4.7)
Requires-Dist: python-dateutil (==2.8.1)
Requires-Dist: pytz (==2020.4)
Requires-Dist: six (==1.15.0)
Provides-Extra: test
Requires-Dist: aiohttp (==3.7.3) ; extra == 'test'
Requires-Dist: async-timeout (==3.0.1) ; extra == 'test'
Requires-Dist: attrs (==20.3.0) ; extra == 'test'
Requires-Dist: certifi (==2020.11.8) ; extra == 'test'
Requires-Dist: chardet (==3.0.4) ; extra == 'test'
Requires-Dist: coverage (==5.3) ; extra == 'test'
Requires-Dist: coveralls (==2.2.0) ; extra == 'test'
Requires-Dist: docopt (==0.6.2) ; extra == 'test'
Requires-Dist: flake8 (==3.8.4) ; extra == 'test'
Requires-Dist: idna (==2.10) ; extra == 'test'
Requires-Dist: importlib-metadata (==2.0.0) ; extra == 'test'
Requires-Dist: iniconfig (==1.1.1) ; extra == 'test'
Requires-Dist: mccabe (==0.6.1) ; extra == 'test'
Requires-Dist: multidict (==5.0.2) ; extra == 'test'
Requires-Dist: packaging (==20.4) ; extra == 'test'
Requires-Dist: pluggy (==0.13.1) ; extra == 'test'
Requires-Dist: py (==1.9.0) ; extra == 'test'
Requires-Dist: pycodestyle (==2.6.0) ; extra == 'test'
Requires-Dist: pyflakes (==2.2.0) ; extra == 'test'
Requires-Dist: pyparsing (==2.4.7) ; extra == 'test'
Requires-Dist: pytest-aiohttp (==0.3.0) ; extra == 'test'
Requires-Dist: pytest-asyncio (==0.14.0) ; extra == 'test'
Requires-Dist: pytest-cov (==2.10.1) ; extra == 'test'
Requires-Dist: pytest-flake8 (==1.0.6) ; extra == 'test'
Requires-Dist: pytest-mock (==3.3.1) ; extra == 'test'
Requires-Dist: pytest (==6.1.2) ; extra == 'test'
Requires-Dist: requests (==2.25.0) ; extra == 'test'
Requires-Dist: six (==1.15.0) ; extra == 'test'
Requires-Dist: toml (==0.10.2) ; extra == 'test'
Requires-Dist: typing-extensions (==3.7.4.3) ; extra == 'test'
Requires-Dist: urllib3 (==1.26.2) ; extra == 'test'
Requires-Dist: yarl (==1.6.3) ; extra == 'test'
Requires-Dist: zipp (==3.4.0) ; extra == 'test'
Requires-Dist: uvloop (==0.14.0) ; (sys_platform != "win32" and sys_platform != "cygwin" and platform_python_implementation != "pypy") and extra == 'test'
